xlib_pillars-1.0.0.dist-info/licenses/LICENSE
xlibrary/__init__.py
xlibrary/py.typed
xlibrary/ai/__init__.py
xlibrary/ai/features.py
xlibrary/ai/manager.py
xlibrary/ai/core/__init__.py
xlibrary/ai/core/base.py
xlibrary/ai/core/config.py
xlibrary/ai/core/exceptions.py
xlibrary/ai/core/models.py
xlibrary/ai/health/__init__.py
xlibrary/ai/health/circuit.py
xlibrary/ai/health/core.py
xlibrary/ai/limits/__init__.py
xlibrary/ai/limits/core.py
xlibrary/ai/limits/providers.py
xlibrary/ai/limits/strategies.py
xlibrary/ai/logging/__init__.py
xlibrary/ai/logging/core.py
xlibrary/ai/logging/formatters.py
xlibrary/ai/logging/handlers.py
xlibrary/ai/metrics/__init__.py
xlibrary/ai/metrics/backends.py
xlibrary/ai/metrics/core.py
xlibrary/ai/providers/__init__.py
xlibrary/ai/providers/claude.py
xlibrary/ai/providers/deepseek.py
xlibrary/ai/providers/mock.py
xlibrary/ai/providers/openai.py
xlibrary/ai/session/__init__.py
xlibrary/ai/session/conversation.py
xlibrary/ai/testing/__init__.py
xlibrary/ai/testing/core.py
xlibrary/ai/testing/interface.py
xlibrary/ai/testing/manager_interface.py
xlibrary/cli/__init__.py
xlibrary/cli/core/__init__.py
xlibrary/cli/core/commands.py
xlibrary/cli/core/framework.py
xlibrary/cli/interactive/__init__.py
xlibrary/cli/interactive/keyboard.py
xlibrary/cli/interactive/navigator.py
xlibrary/cli/ui/__init__.py
xlibrary/cli/ui/dashboard.py
xlibrary/cli/ui/menu.py
xlibrary/cli/ui/output.py
xlibrary/cli/ui/progress.py
xlibrary/communication/__init__.py
xlibrary/communication/cli/__init__.py
xlibrary/communication/cli/integration_pattern.py
xlibrary/communication/core/exceptions.py
xlibrary/communication/core/manager.py
xlibrary/communication/core/message.py
xlibrary/communication/email/__init__.py
xlibrary/communication/email/core/__init__.py
xlibrary/communication/email/core/attachments.py
xlibrary/communication/email/core/query.py
xlibrary/communication/email/providers/__init__.py
xlibrary/communication/email/providers/gmail.py
xlibrary/config/__init__.py
xlibrary/config/helpers.py
xlib_pillars-1.0.0.dist-info/METADATA
xlib_pillars-1.0.0.dist-info/WHEEL
xlib_pillars-1.0.0.dist-info/top_level.txt
xlib_pillars-1.0.0.dist-info/RECORD
