Metadata-Version: 2.4
Name: xlib-pillars
Version: 1.0.0
Summary: xlib-pillars: A comprehensive library ecosystem with modular pillars for modern Python development
Author-email: xlibrary <contact@xlibrary.dev>
License: MIT
Project-URL: Homepage, https://github.com/ileswade/xlibrary
Project-URL: Repository, https://github.com/ileswade/xlibrary
Project-URL: Documentation, https://github.com/ileswade/xlibrary/blob/main/README.md
Project-URL: Bug Reports, https://github.com/ileswade/xlibrary/issues
Keywords: xlib-pillars,xlibrary,ecosystem,ai,config,pillars,claude,openai,deepseek,media,download,encryption,cli
Classifier: Development Status :: 4 - Beta
Classifier: Intended Audience :: Developers
Classifier: License :: OSI Approved :: MIT License
Classifier: Programming Language :: Python :: 3
Classifier: Programming Language :: Python :: 3.8
Classifier: Programming Language :: Python :: 3.9
Classifier: Programming Language :: Python :: 3.10
Classifier: Programming Language :: Python :: 3.11
Classifier: Programming Language :: Python :: 3.12
Classifier: Topic :: Software Development :: Libraries :: Python Modules
Classifier: Topic :: Scientific/Engineering :: Artificial Intelligence
Classifier: Topic :: System :: Systems Administration
Classifier: Topic :: Utilities
Classifier: Topic :: Multimedia :: Video
Classifier: Topic :: Multimedia :: Graphics
Classifier: Topic :: Security :: Cryptography
Classifier: Topic :: Internet :: WWW/HTTP :: Dynamic Content
Requires-Python: >=3.8
License-File: LICENSE
Requires-Dist: requests>=2.28.0
Requires-Dist: typing-extensions>=4.0.0; python_version < "3.10"
Provides-Extra: ai
Requires-Dist: anthropic>=0.25.0; extra == "ai"
Requires-Dist: openai>=1.0.0; extra == "ai"
Requires-Dist: tiktoken>=0.4.0; extra == "ai"
Provides-Extra: claude
Requires-Dist: anthropic>=0.25.0; extra == "claude"
Provides-Extra: openai
Requires-Dist: openai>=1.0.0; extra == "openai"
Requires-Dist: tiktoken>=0.4.0; extra == "openai"
Provides-Extra: deepseek
Requires-Dist: openai>=1.0.0; extra == "deepseek"
Requires-Dist: tiktoken>=0.4.0; extra == "deepseek"
Provides-Extra: config
Requires-Dist: omegaconf>=2.3.0; extra == "config"
Requires-Dist: toml>=0.10.2; extra == "config"
Requires-Dist: tomli>=2.0.1; python_version < "3.11" and extra == "config"
Provides-Extra: download
Requires-Dist: yt-dlp>=2023.12.30; extra == "download"
Requires-Dist: rich>=13.0.0; extra == "download"
Requires-Dist: tqdm>=4.65.0; extra == "download"
Requires-Dist: aiohttp>=3.8.0; extra == "download"
Requires-Dist: aiofiles>=0.8.0; extra == "download"
Provides-Extra: media
Requires-Dist: Pillow>=10.0.0; extra == "media"
Requires-Dist: numpy>=1.24.0; extra == "media"
Requires-Dist: moviepy>=1.0.3; extra == "media"
Requires-Dist: opencv-python>=4.7.0; extra == "media"
Provides-Extra: encryption
Requires-Dist: cryptography>=41.0.0; extra == "encryption"
Provides-Extra: files
Requires-Dist: python-magic>=0.4.27; extra == "files"
Requires-Dist: python-magic-bin>=0.4.14; platform_system == "Windows" and extra == "files"
Provides-Extra: imports
Requires-Dist: python-magic>=0.4.27; extra == "imports"
Requires-Dist: python-magic-bin>=0.4.14; platform_system == "Windows" and extra == "imports"
Requires-Dist: watchdog>=3.0.0; extra == "imports"
Provides-Extra: pipeline
Requires-Dist: pydantic>=2.0.0; extra == "pipeline"
Provides-Extra: cli
Requires-Dist: click>=8.0.0; extra == "cli"
Requires-Dist: rich>=13.0.0; extra == "cli"
Provides-Extra: all
Requires-Dist: anthropic>=0.25.0; extra == "all"
Requires-Dist: openai>=1.0.0; extra == "all"
Requires-Dist: tiktoken>=0.4.0; extra == "all"
Requires-Dist: omegaconf>=2.3.0; extra == "all"
Requires-Dist: toml>=0.10.2; extra == "all"
Requires-Dist: tomli>=2.0.1; python_version < "3.11" and extra == "all"
Requires-Dist: yt-dlp>=2023.12.30; extra == "all"
Requires-Dist: rich>=13.0.0; extra == "all"
Requires-Dist: tqdm>=4.65.0; extra == "all"
Requires-Dist: aiohttp>=3.8.0; extra == "all"
Requires-Dist: aiofiles>=0.8.0; extra == "all"
Requires-Dist: Pillow>=10.0.0; extra == "all"
Requires-Dist: numpy>=1.24.0; extra == "all"
Requires-Dist: moviepy>=1.0.3; extra == "all"
Requires-Dist: opencv-python>=4.7.0; extra == "all"
Requires-Dist: cryptography>=41.0.0; extra == "all"
Requires-Dist: python-magic>=0.4.27; extra == "all"
Requires-Dist: python-magic-bin>=0.4.14; platform_system == "Windows" and extra == "all"
Requires-Dist: python-magic>=0.4.27; extra == "all"
Requires-Dist: python-magic-bin>=0.4.14; platform_system == "Windows" and extra == "all"
Requires-Dist: watchdog>=3.0.0; extra == "all"
Requires-Dist: pydantic>=2.0.0; extra == "all"
Requires-Dist: click>=8.0.0; extra == "all"
Provides-Extra: dev
Requires-Dist: pytest>=7.0.0; extra == "dev"
Requires-Dist: pytest-asyncio>=0.21.0; extra == "dev"
Requires-Dist: pytest-cov>=4.0.0; extra == "dev"
Requires-Dist: black>=22.0.0; extra == "dev"
Requires-Dist: flake8>=4.0.0; extra == "dev"
Requires-Dist: mypy>=0.991; extra == "dev"
Requires-Dist: twine>=4.0.0; extra == "dev"
Requires-Dist: build>=0.10.0; extra == "dev"
Dynamic: license-file
